SCNN_Lane_Detection/__init__.py
SCNN_Lane_Detection/model.py
SCNN_Lane_Detection/utils/__init__.py
SCNN_Lane_Detection/utils/lr_scheduler.py
SCNN_Lane_Detection/utils/tensorboard.py
SCNN_Lane_Detection/utils/prob2lines/__init__.py
SCNN_Lane_Detection/utils/prob2lines/getLane.py
SCNN_Lane_Detection/utils/transforms/__init__.py
SCNN_Lane_Detection/utils/transforms/data_augmentation.py
SCNN_Lane_Detection/utils/transforms/transforms.py
laneDetection-0.0.2.dist-info/LICENSE
laneDetection-0.0.2.dist-info/METADATA
laneDetection-0.0.2.dist-info/WHEEL
laneDetection-0.0.2.dist-info/top_level.txt
laneDetection-0.0.2.dist-info/RECORD
