Metadata-Version: 2.1
Name: laneDetection
Version: 0.0.2
Summary: Lane Detection Library
Home-page: UNKNOWN
Author: UNKNOWN
Author-email: UNKNOWN
License: UNKNOWN
Platform: UNKNOWN
